src/Topsis-Shikha-102016009.py
Topsis_Shikha_102016009-1.0.0.dist-info/LICENSE.md
Topsis_Shikha_102016009-1.0.0.dist-info/METADATA
Topsis_Shikha_102016009-1.0.0.dist-info/WHEEL
Topsis_Shikha_102016009-1.0.0.dist-info/top_level.txt
Topsis_Shikha_102016009-1.0.0.dist-info/RECORD
