Metadata-Version: 2.1
Name: Topsis-Shikha-102016009
Version: 1.0.0
Summary: A package for topsis score generation.
Author: Shikha
Author-email: sshikha_be20@thapar.edu
License: MIT License        
License-File: LICENSE.md
Requires-Dist: pandas
Requires-Dist: numpy
